nens_meta/__init__.py
nens_meta/nens_toml.py
nens_meta/pyproject_toml.py
nens_meta/update_project.py
nens_meta/utils.py
nens_meta/tests/__init__.py
nens_meta/tests/test_nens_toml.py
nens_meta/tests/test_pyproject_toml.py
nens_meta/tests/test_update_project.py
nens_meta/tests/test_utils.py
nens_meta-1.0.dist-info/licenses/LICENSE
nens_meta-1.0.dist-info/METADATA
nens_meta-1.0.dist-info/WHEEL
nens_meta-1.0.dist-info/entry_points.txt
nens_meta-1.0.dist-info/top_level.txt
nens_meta-1.0.dist-info/RECORD
