Metadata-Version: 2.4
Name: nens-meta
Version: 1.0
Summary: Basic project automation and update tool
Author-email: Reinout van Rees <reinout.vanrees@nelen-schuurmans.nl>
License: MIT
Project-URL: Documentation, https://nens-meta.readthedocs.io/
Project-URL: Repository, https://github.com/nens/nens-meta
Project-URL: Changelog, https://github.com/nens/nens-meta/blob/main/CHANGES.md
Requires-Python: >=3.11
License-File: LICENSE
Requires-Dist: Jinja2
Requires-Dist: tomlkit
Requires-Dist: typer
Dynamic: license-file
